aplex/__init__.py
aplex/__version__.py
aplex/compat.py
aplex/executor.py
aplex/futures.py
aplex/load_balancers.py
aplex/process.py
aplex/protect.py
aplex/py35_support.py
aplex/thread.py
asyncpool/__init__.py
asyncpool/__version__.py
asyncpool/compat.py
asyncpool/executor.py
asyncpool/futures.py
asyncpool/load_balancers.py
asyncpool/process.py
asyncpool/protect.py
asyncpool/py35_support.py
asyncpool/thread.py
aplex-1.0.1.dist-info/LICENSE
aplex-1.0.1.dist-info/METADATA
aplex-1.0.1.dist-info/WHEEL
aplex-1.0.1.dist-info/top_level.txt
aplex-1.0.1.dist-info/RECORD
