Metadata-Version: 2.1
Name: aplex
Version: 1.0.1
Summary: Run your coroutines and functions in child process or thread like the way using concurrent.futures.
Home-page: https://github.com/lunluen/aplex
Author: Lunluen
Author-email: mas581301@gmail.com
License: MIT
Platform: UNKNOWN
Classifier: Development Status :: 4 - Beta
Classifier: Framework :: AsyncIO
Classifier: Intended Audience :: Developers
Classifier: License :: OSI Approved :: MIT License
Classifier: Programming Language :: Python
Classifier: Programming Language :: Python :: 3.5
Classifier: Programming Language :: Python :: 3.6
Classifier: Programming Language :: Python :: 3.7
Classifier: Programming Language :: Python :: Implementation :: CPython
Classifier: Topic :: Software Development :: Libraries :: Python Modules
Requires-Python: >=3.5.0
Provides-Extra: uvloop
Requires-Dist: uvloop ; extra == 'uvloop'
